{
"type": "FeatureCollection",
"name": "xenos",
"crs": { "type": "name", "properties": { "name": "urn:ogc:def:crs:OGC:1.3:CRS84" } },
"features": [
{ "type": "Feature", "properties": { "id": 1 }, "geometry": { "type": "Point", "coordinates": [ 13.3748301, 52.5082404 ] } },
{ "type": "Feature", "properties": { "id": 2 }, "geometry": { "type": "Point", "coordinates": [ 13.432503, 52.4823147 ] } },
{ "type": "Feature", "properties": { "id": 3 }, "geometry": { "type": "Point", "coordinates": [ 13.3047275, 52.5091705 ] } },
{ "type": "Feature", "properties": { "id": 4 }, "geometry": { "type": "Point", "coordinates": [ 13.3248923, 52.4626198 ] } }
]
}
