{
"type": "FeatureCollection",
"name": "xenos",
"crs": { "type": "name", "properties": { "name": "urn:ogc:def:crs:OGC:1.3:CRS84" } },
"features": [
{ "type": "Feature", "properties": { "sname": "BE" }, "geometry": { "type": "Point", "coordinates": [ 13.37483, 52.50824 ] } },
{ "type": "Feature", "properties": { "sname": "BE" }, "geometry": { "type": "Point", "coordinates": [ 13.4325, 52.48231 ] } },
{ "type": "Feature", "properties": { "sname": "BE" }, "geometry": { "type": "Point", "coordinates": [ 13.30473, 52.50917 ] } },
{ "type": "Feature", "properties": { "sname": "BE" }, "geometry": { "type": "Point", "coordinates": [ 13.32489, 52.46262 ] } }
]
}
